kabuzi/__init__.py
kabuzi/dl.py
kabuzi/docop.py
kabuzi-0.0.2.dist-info/METADATA
kabuzi-0.0.2.dist-info/WHEEL
kabuzi-0.0.2.dist-info/top_level.txt
kabuzi-0.0.2.dist-info/RECORD
