Metadata-Version: 2.1
Name: kabuzi
Version: 0.0.2
Summary: play with python
Home-page: UNKNOWN
Author: kabu2i
Author-email: test@test.com
License: MIT-0
Platform: UNKNOWN
